morethansentiments.py
morethansentiments-0.3.3.dist-info/LICENSE
morethansentiments-0.3.3.dist-info/METADATA
morethansentiments-0.3.3.dist-info/WHEEL
morethansentiments-0.3.3.dist-info/top_level.txt
morethansentiments-0.3.3.dist-info/RECORD
