Metadata-Version: 2.1
Name: morethansentiments
Version: 0.3.3
Summary: An NLP python package for computing Boilerplate score and many other text features.
Home-page: https://github.com/jinhangjiang/morethansentiments
Author: Jinhang Jiang, Karthik Srinivasan
Author-email: jinhang@asu.edu
License: UNKNOWN
Keywords: Text Mining,Data Science,Natural Language Processing,Accounting
Platform: UNKNOWN
Classifier: Development Status :: 4 - Beta
Classifier: Programming Language :: Python :: 3
Classifier: Programming Language :: Python :: 3.6
Classifier: Programming Language :: Python :: 3.7
Classifier: Programming Language :: Python :: 3.8
Classifier: Programming Language :: Python :: 3.9
Classifier: License :: OSI Approved :: BSD License
Classifier: Intended Audience :: Developers
Classifier: Intended Audience :: Other Audience
Classifier: Intended Audience :: Science/Research
Classifier: Intended Audience :: Education
Classifier: Topic :: Text Processing
Classifier: Operating System :: Microsoft :: Windows
Classifier: Operating System :: OS Independent
Requires-Dist: tqdm (>=4.59.0)
Requires-Dist: spacy (>=3.3.0)
Requires-Dist: pandas (>=1.2.4)
Requires-Dist: nltk (>=3.6.1)
